README.md
setup.py
zaranian/__init__.py
zaranian.egg-info/PKG-INFO
zaranian.egg-info/SOURCES.txt
zaranian.egg-info/dependency_links.txt
zaranian.egg-info/top_level.txt