Metadata-Version: 2.1
Name: zaranian
Version: 1.1.2
Summary: ramを割り当ててvramにするユーティリティパッケージ windowsのみ対応
Home-page: https://github.com/zakogarisuki2/zaranian
Author: グラファイト
Author-email: gymk@gaypan.com
Classifier: Programming Language :: Python :: 3
Classifier: Operating System :: OS Independent
Requires-Python: >=3.6
